package com.xiaomi.gamecenter.sdk.utils;

import android.content.Context;

final class k
  implements Runnable
{
  k(Context paramContext, int paramInt, String paramString, boolean paramBoolean) {}
  
  /* Error */
  public final void run()
  {
    // Byte code:
    //   0: aconst_null
    //   1: astore 4
    //   3: aconst_null
    //   4: astore 6
    //   6: aload 4
    //   8: astore_3
    //   9: new 35	java/util/HashMap
    //   12: dup
    //   13: invokespecial 36	java/util/HashMap:<init>	()V
    //   16: astore 7
    //   18: aload 4
    //   20: astore_3
    //   21: aload 7
    //   23: ldc 38
    //   25: aload_0
    //   26: getfield 18	com/xiaomi/gamecenter/sdk/utils/k:a	Landroid/content/Context;
    //   29: invokestatic 44	com/xiaomi/gamecenter/sdk/utils/b:f	(Landroid/content/Context;)Ljava/lang/String;
    //   32: invokevirtual 48	java/util/HashMap:put	(Ljava/lang/Object;Ljava/lang/Object;)Ljava/lang/Object;
    //   35: pop
    //   36: aload 4
    //   38: astore_3
    //   39: aload 7
    //   41: ldc 50
    //   43: invokestatic 55	com/xiaomi/gamecenter/sdk/utils/ReporterUtils:a	()Ljava/lang/String;
    //   46: invokevirtual 48	java/util/HashMap:put	(Ljava/lang/Object;Ljava/lang/Object;)Ljava/lang/Object;
    //   49: pop
    //   50: aload 4
    //   52: astore_3
    //   53: aload 7
    //   55: ldc 57
    //   57: aload_0
    //   58: getfield 18	com/xiaomi/gamecenter/sdk/utils/k:a	Landroid/content/Context;
    //   61: invokestatic 44	com/xiaomi/gamecenter/sdk/utils/b:f	(Landroid/content/Context;)Ljava/lang/String;
    //   64: invokevirtual 48	java/util/HashMap:put	(Ljava/lang/Object;Ljava/lang/Object;)Ljava/lang/Object;
    //   67: pop
    //   68: aload 4
    //   70: astore_3
    //   71: aload 7
    //   73: ldc 59
    //   75: getstatic 62	com/xiaomi/gamecenter/sdk/utils/b:m	Ljava/lang/String;
    //   78: invokevirtual 48	java/util/HashMap:put	(Ljava/lang/Object;Ljava/lang/Object;)Ljava/lang/Object;
    //   81: pop
    //   82: aload 4
    //   84: astore_3
    //   85: aload 7
    //   87: ldc 64
    //   89: aload_0
    //   90: getfield 20	com/xiaomi/gamecenter/sdk/utils/k:b	I
    //   93: invokestatic 70	java/lang/String:valueOf	(I)Ljava/lang/String;
    //   96: invokevirtual 48	java/util/HashMap:put	(Ljava/lang/Object;Ljava/lang/Object;)Ljava/lang/Object;
    //   99: pop
    //   100: aload 4
    //   102: astore_3
    //   103: aload 7
    //   105: ldc 72
    //   107: aload_0
    //   108: getfield 22	com/xiaomi/gamecenter/sdk/utils/k:c	Ljava/lang/String;
    //   111: invokevirtual 48	java/util/HashMap:put	(Ljava/lang/Object;Ljava/lang/Object;)Ljava/lang/Object;
    //   114: pop
    //   115: aload 4
    //   117: astore_3
    //   118: aload_0
    //   119: getfield 24	com/xiaomi/gamecenter/sdk/utils/k:d	Z
    //   122: istore_2
    //   123: iload_2
    //   124: ifeq +29 -> 153
    //   127: aload 4
    //   129: astore_3
    //   130: invokestatic 74	com/xiaomi/gamecenter/sdk/utils/ReporterUtils:b	()Ljava/lang/String;
    //   133: invokestatic 80	android/text/TextUtils:isEmpty	(Ljava/lang/CharSequence;)Z
    //   136: ifne +17 -> 153
    //   139: aload 4
    //   141: astore_3
    //   142: aload 7
    //   144: ldc 82
    //   146: invokestatic 74	com/xiaomi/gamecenter/sdk/utils/ReporterUtils:b	()Ljava/lang/String;
    //   149: invokevirtual 48	java/util/HashMap:put	(Ljava/lang/Object;Ljava/lang/Object;)Ljava/lang/Object;
    //   152: pop
    //   153: aload 4
    //   155: astore_3
    //   156: aload 7
    //   158: ldc 84
    //   160: ldc 86
    //   162: invokevirtual 48	java/util/HashMap:put	(Ljava/lang/Object;Ljava/lang/Object;)Ljava/lang/Object;
    //   165: pop
    //   166: aload 4
    //   168: astore_3
    //   169: aload 7
    //   171: ldc 88
    //   173: aload_0
    //   174: getfield 18	com/xiaomi/gamecenter/sdk/utils/k:a	Landroid/content/Context;
    //   177: invokestatic 93	com/wali/gamecenter/report/utils/TelUtils:getSIMOperatorName	(Landroid/content/Context;)Ljava/lang/String;
    //   180: invokevirtual 48	java/util/HashMap:put	(Ljava/lang/Object;Ljava/lang/Object;)Ljava/lang/Object;
    //   183: pop
    //   184: aload 4
    //   186: astore_3
    //   187: aload 7
    //   189: ldc 95
    //   191: ldc 97
    //   193: invokevirtual 48	java/util/HashMap:put	(Ljava/lang/Object;Ljava/lang/Object;)Ljava/lang/Object;
    //   196: pop
    //   197: aload 4
    //   199: astore_3
    //   200: new 99	org/json/JSONObject
    //   203: dup
    //   204: invokespecial 100	org/json/JSONObject:<init>	()V
    //   207: astore 5
    //   209: aload 4
    //   211: astore_3
    //   212: aload 5
    //   214: ldc 102
    //   216: aload_0
    //   217: getfield 18	com/xiaomi/gamecenter/sdk/utils/k:a	Landroid/content/Context;
    //   220: invokevirtual 107	android/content/Context:getPackageName	()Ljava/lang/String;
    //   223: invokevirtual 110	org/json/JSONObject:put	(Ljava/lang/String;Ljava/lang/Object;)Lorg/json/JSONObject;
    //   226: pop
    //   227: aload 4
    //   229: astore_3
    //   230: aload 5
    //   232: ldc 112
    //   234: ldc 114
    //   236: invokevirtual 110	org/json/JSONObject:put	(Ljava/lang/String;Ljava/lang/Object;)Lorg/json/JSONObject;
    //   239: pop
    //   240: aload 4
    //   242: astore_3
    //   243: aload 5
    //   245: ldc 116
    //   247: ldc 118
    //   249: invokevirtual 110	org/json/JSONObject:put	(Ljava/lang/String;Ljava/lang/Object;)Lorg/json/JSONObject;
    //   252: pop
    //   253: aload 4
    //   255: astore_3
    //   256: aload 5
    //   258: ldc 120
    //   260: invokestatic 126	java/lang/System:currentTimeMillis	()J
    //   263: invokestatic 129	java/lang/String:valueOf	(J)Ljava/lang/String;
    //   266: invokevirtual 110	org/json/JSONObject:put	(Ljava/lang/String;Ljava/lang/Object;)Lorg/json/JSONObject;
    //   269: pop
    //   270: aload 4
    //   272: astore_3
    //   273: aload 7
    //   275: ldc -125
    //   277: aload 5
    //   279: invokevirtual 134	org/json/JSONObject:toString	()Ljava/lang/String;
    //   282: invokevirtual 48	java/util/HashMap:put	(Ljava/lang/Object;Ljava/lang/Object;)Ljava/lang/Object;
    //   285: pop
    //   286: aload 4
    //   288: astore_3
    //   289: aload 7
    //   291: ldc -120
    //   293: getstatic 139	com/xiaomi/gamecenter/sdk/utils/b:j	Ljava/lang/String;
    //   296: invokevirtual 48	java/util/HashMap:put	(Ljava/lang/Object;Ljava/lang/Object;)Ljava/lang/Object;
    //   299: pop
    //   300: aload 4
    //   302: astore_3
    //   303: aload 7
    //   305: ldc -115
    //   307: getstatic 144	com/xiaomi/gamecenter/sdk/utils/b:r	Ljava/lang/String;
    //   310: invokevirtual 48	java/util/HashMap:put	(Ljava/lang/Object;Ljava/lang/Object;)Ljava/lang/Object;
    //   313: pop
    //   314: aload 4
    //   316: astore_3
    //   317: aload 7
    //   319: ldc -110
    //   321: getstatic 149	com/xiaomi/gamecenter/sdk/utils/b:q	Ljava/lang/String;
    //   324: invokevirtual 48	java/util/HashMap:put	(Ljava/lang/Object;Ljava/lang/Object;)Ljava/lang/Object;
    //   327: pop
    //   328: aload 4
    //   330: astore_3
    //   331: aload 7
    //   333: ldc -105
    //   335: invokestatic 153	com/xiaomi/gamecenter/sdk/utils/ReporterUtils:c	()Ljava/lang/String;
    //   338: invokevirtual 48	java/util/HashMap:put	(Ljava/lang/Object;Ljava/lang/Object;)Ljava/lang/Object;
    //   341: pop
    //   342: aload 4
    //   344: astore_3
    //   345: aload 7
    //   347: ldc -101
    //   349: ldc -99
    //   351: invokevirtual 48	java/util/HashMap:put	(Ljava/lang/Object;Ljava/lang/Object;)Ljava/lang/Object;
    //   354: pop
    //   355: aload 4
    //   357: astore_3
    //   358: aload 7
    //   360: ldc -97
    //   362: ldc -95
    //   364: invokevirtual 48	java/util/HashMap:put	(Ljava/lang/Object;Ljava/lang/Object;)Ljava/lang/Object;
    //   367: pop
    //   368: aload 4
    //   370: astore_3
    //   371: aload 7
    //   373: ldc -93
    //   375: aload_0
    //   376: getfield 18	com/xiaomi/gamecenter/sdk/utils/k:a	Landroid/content/Context;
    //   379: invokestatic 166	com/wali/gamecenter/report/utils/TelUtils:get_device_agent_	(Landroid/content/Context;)Ljava/lang/String;
    //   382: invokevirtual 48	java/util/HashMap:put	(Ljava/lang/Object;Ljava/lang/Object;)Ljava/lang/Object;
    //   385: pop
    //   386: aload 4
    //   388: astore_3
    //   389: aload 7
    //   391: ldc -88
    //   393: ldc -86
    //   395: invokevirtual 48	java/util/HashMap:put	(Ljava/lang/Object;Ljava/lang/Object;)Ljava/lang/Object;
    //   398: pop
    //   399: aload 4
    //   401: astore_3
    //   402: new 172	java/lang/StringBuilder
    //   405: dup
    //   406: invokespecial 173	java/lang/StringBuilder:<init>	()V
    //   409: astore 5
    //   411: aload 4
    //   413: astore_3
    //   414: aload 7
    //   416: invokevirtual 177	java/util/HashMap:entrySet	()Ljava/util/Set;
    //   419: invokeinterface 183 1 0
    //   424: astore 7
    //   426: aload 4
    //   428: astore_3
    //   429: aload 7
    //   431: invokeinterface 189 1 0
    //   436: ifeq +187 -> 623
    //   439: aload 4
    //   441: astore_3
    //   442: aload 7
    //   444: invokeinterface 193 1 0
    //   449: checkcast 195	java/util/Map$Entry
    //   452: astore 8
    //   454: aload 4
    //   456: astore_3
    //   457: aload 5
    //   459: invokevirtual 199	java/lang/StringBuilder:length	()I
    //   462: ifle +14 -> 476
    //   465: aload 4
    //   467: astore_3
    //   468: aload 5
    //   470: ldc -55
    //   472: invokevirtual 205	java/lang/StringBuilder:append	(Ljava/lang/String;)Ljava/lang/StringBuilder;
    //   475: pop
    //   476: aload 4
    //   478: astore_3
    //   479: aload 8
    //   481: invokeinterface 208 1 0
    //   486: checkcast 210	java/lang/CharSequence
    //   489: invokestatic 80	android/text/TextUtils:isEmpty	(Ljava/lang/CharSequence;)Z
    //   492: ifne -66 -> 426
    //   495: aload 4
    //   497: astore_3
    //   498: aload 5
    //   500: aload 8
    //   502: invokeinterface 213 1 0
    //   507: checkcast 66	java/lang/String
    //   510: invokevirtual 205	java/lang/StringBuilder:append	(Ljava/lang/String;)Ljava/lang/StringBuilder;
    //   513: pop
    //   514: aload 4
    //   516: astore_3
    //   517: aload 5
    //   519: ldc -41
    //   521: invokevirtual 205	java/lang/StringBuilder:append	(Ljava/lang/String;)Ljava/lang/StringBuilder;
    //   524: pop
    //   525: aload 4
    //   527: astore_3
    //   528: aload 5
    //   530: aload 8
    //   532: invokeinterface 208 1 0
    //   537: checkcast 66	java/lang/String
    //   540: ldc -39
    //   542: invokestatic 223	java/net/URLEncoder:encode	(Ljava/lang/String;Ljava/lang/String;)Ljava/lang/String;
    //   545: invokevirtual 205	java/lang/StringBuilder:append	(Ljava/lang/String;)Ljava/lang/StringBuilder;
    //   548: pop
    //   549: goto -123 -> 426
    //   552: astore 8
    //   554: aload 4
    //   556: astore_3
    //   557: aload 8
    //   559: invokevirtual 226	java/lang/Exception:printStackTrace	()V
    //   562: goto -136 -> 426
    //   565: astore 5
    //   567: aload 6
    //   569: astore 4
    //   571: aload 4
    //   573: astore_3
    //   574: aload 5
    //   576: invokevirtual 227	java/lang/Throwable:printStackTrace	()V
    //   579: aload 4
    //   581: ifnull +8 -> 589
    //   584: aload 4
    //   586: invokevirtual 232	java/net/HttpURLConnection:disconnect	()V
    //   589: return
    //   590: astore 5
    //   592: aload 4
    //   594: astore_3
    //   595: aload 5
    //   597: invokevirtual 226	java/lang/Exception:printStackTrace	()V
    //   600: goto -447 -> 153
    //   603: astore 4
    //   605: aload_3
    //   606: astore 5
    //   608: aload 4
    //   610: astore_3
    //   611: aload 5
    //   613: ifnull +8 -> 621
    //   616: aload 5
    //   618: invokevirtual 232	java/net/HttpURLConnection:disconnect	()V
    //   621: aload_3
    //   622: athrow
    //   623: aload 4
    //   625: astore_3
    //   626: new 234	java/net/URL
    //   629: dup
    //   630: new 172	java/lang/StringBuilder
    //   633: dup
    //   634: ldc -20
    //   636: invokespecial 239	java/lang/StringBuilder:<init>	(Ljava/lang/String;)V
    //   639: aload 5
    //   641: invokevirtual 240	java/lang/StringBuilder:toString	()Ljava/lang/String;
    //   644: invokevirtual 205	java/lang/StringBuilder:append	(Ljava/lang/String;)Ljava/lang/StringBuilder;
    //   647: invokevirtual 240	java/lang/StringBuilder:toString	()Ljava/lang/String;
    //   650: invokespecial 241	java/net/URL:<init>	(Ljava/lang/String;)V
    //   653: invokevirtual 245	java/net/URL:openConnection	()Ljava/net/URLConnection;
    //   656: checkcast 229	java/net/HttpURLConnection
    //   659: astore 4
    //   661: aload 4
    //   663: invokevirtual 248	java/net/HttpURLConnection:getResponseCode	()I
    //   666: istore_1
    //   667: new 172	java/lang/StringBuilder
    //   670: dup
    //   671: ldc -6
    //   673: invokespecial 239	java/lang/StringBuilder:<init>	(Ljava/lang/String;)V
    //   676: iload_1
    //   677: invokevirtual 253	java/lang/StringBuilder:append	(I)Ljava/lang/StringBuilder;
    //   680: ldc -1
    //   682: invokevirtual 205	java/lang/StringBuilder:append	(Ljava/lang/String;)Ljava/lang/StringBuilder;
    //   685: aload_0
    //   686: getfield 20	com/xiaomi/gamecenter/sdk/utils/k:b	I
    //   689: invokevirtual 253	java/lang/StringBuilder:append	(I)Ljava/lang/StringBuilder;
    //   692: invokevirtual 240	java/lang/StringBuilder:toString	()Ljava/lang/String;
    //   695: invokestatic 259	cn/com/wali/basetool/log/Logger:b	(Ljava/lang/String;)V
    //   698: aload 4
    //   700: ifnull -111 -> 589
    //   703: aload 4
    //   705: invokevirtual 232	java/net/HttpURLConnection:disconnect	()V
    //   708: return
    //   709: astore_3
    //   710: aload_3
    //   711: invokevirtual 226	java/lang/Exception:printStackTrace	()V
    //   714: return
    //   715: astore_3
    //   716: aload_3
    //   717: invokevirtual 226	java/lang/Exception:printStackTrace	()V
    //   720: return
    //   721: astore 4
    //   723: aload 4
    //   725: invokevirtual 226	java/lang/Exception:printStackTrace	()V
    //   728: goto -107 -> 621
    //   731: astore_3
    //   732: aload 4
    //   734: astore 5
    //   736: goto -125 -> 611
    //   739: astore 5
    //   741: goto -170 -> 571
    // Local variable table:
    //   start	length	slot	name	signature
    //   0	744	0	this	k
    //   666	11	1	i	int
    //   122	2	2	bool	boolean
    //   8	618	3	localObject1	Object
    //   709	2	3	localException1	Exception
    //   715	2	3	localException2	Exception
    //   731	1	3	localObject2	Object
    //   1	592	4	localObject3	Object
    //   603	21	4	localObject4	Object
    //   659	45	4	localHttpURLConnection	java.net.HttpURLConnection
    //   721	12	4	localException3	Exception
    //   207	322	5	localObject5	Object
    //   565	10	5	localThrowable1	Throwable
    //   590	6	5	localException4	Exception
    //   606	129	5	localObject6	Object
    //   739	1	5	localThrowable2	Throwable
    //   4	564	6	localObject7	Object
    //   16	427	7	localObject8	Object
    //   452	79	8	localEntry	java.util.Map.Entry
    //   552	6	8	localException5	Exception
    // Exception table:
    //   from	to	target	type
    //   528	549	552	java/lang/Exception
    //   9	18	565	java/lang/Throwable
    //   21	36	565	java/lang/Throwable
    //   39	50	565	java/lang/Throwable
    //   53	68	565	java/lang/Throwable
    //   71	82	565	java/lang/Throwable
    //   85	100	565	java/lang/Throwable
    //   103	115	565	java/lang/Throwable
    //   118	123	565	java/lang/Throwable
    //   130	139	565	java/lang/Throwable
    //   142	153	565	java/lang/Throwable
    //   156	166	565	java/lang/Throwable
    //   169	184	565	java/lang/Throwable
    //   187	197	565	java/lang/Throwable
    //   200	209	565	java/lang/Throwable
    //   212	227	565	java/lang/Throwable
    //   230	240	565	java/lang/Throwable
    //   243	253	565	java/lang/Throwable
    //   256	270	565	java/lang/Throwable
    //   273	286	565	java/lang/Throwable
    //   289	300	565	java/lang/Throwable
    //   303	314	565	java/lang/Throwable
    //   317	328	565	java/lang/Throwable
    //   331	342	565	java/lang/Throwable
    //   345	355	565	java/lang/Throwable
    //   358	368	565	java/lang/Throwable
    //   371	386	565	java/lang/Throwable
    //   389	399	565	java/lang/Throwable
    //   402	411	565	java/lang/Throwable
    //   414	426	565	java/lang/Throwable
    //   429	439	565	java/lang/Throwable
    //   442	454	565	java/lang/Throwable
    //   457	465	565	java/lang/Throwable
    //   468	476	565	java/lang/Throwable
    //   479	495	565	java/lang/Throwable
    //   498	514	565	java/lang/Throwable
    //   517	525	565	java/lang/Throwable
    //   528	549	565	java/lang/Throwable
    //   557	562	565	java/lang/Throwable
    //   595	600	565	java/lang/Throwable
    //   626	661	565	java/lang/Throwable
    //   130	139	590	java/lang/Exception
    //   142	153	590	java/lang/Exception
    //   9	18	603	finally
    //   21	36	603	finally
    //   39	50	603	finally
    //   53	68	603	finally
    //   71	82	603	finally
    //   85	100	603	finally
    //   103	115	603	finally
    //   118	123	603	finally
    //   130	139	603	finally
    //   142	153	603	finally
    //   156	166	603	finally
    //   169	184	603	finally
    //   187	197	603	finally
    //   200	209	603	finally
    //   212	227	603	finally
    //   230	240	603	finally
    //   243	253	603	finally
    //   256	270	603	finally
    //   273	286	603	finally
    //   289	300	603	finally
    //   303	314	603	finally
    //   317	328	603	finally
    //   331	342	603	finally
    //   345	355	603	finally
    //   358	368	603	finally
    //   371	386	603	finally
    //   389	399	603	finally
    //   402	411	603	finally
    //   414	426	603	finally
    //   429	439	603	finally
    //   442	454	603	finally
    //   457	465	603	finally
    //   468	476	603	finally
    //   479	495	603	finally
    //   498	514	603	finally
    //   517	525	603	finally
    //   528	549	603	finally
    //   557	562	603	finally
    //   574	579	603	finally
    //   595	600	603	finally
    //   626	661	603	finally
    //   703	708	709	java/lang/Exception
    //   584	589	715	java/lang/Exception
    //   616	621	721	java/lang/Exception
    //   661	698	731	finally
    //   661	698	739	java/lang/Throwable
  }
}


/* Location:              C:\Users\Administrator\Desktop\apk\dex2jar\classes-dex2jar.jar!\com\xiaomi\gamecenter\sdk\utils\k.class
 * Java compiler version: 6 (50.0)
 * JD-Core Version:       0.7.1
 */